algebra_calculator/__init__.py
algebra_calculator/admin.py
algebra_calculator/apps.py
algebra_calculator/models.py
algebra_calculator/tests.py
algebra_calculator/views.py
algebra_calculator/migrations/__init__.py
ui/__init__.py
ui/admin.py
ui/apps.py
ui/models.py
ui/tests.py
ui/urls.py
ui/views.py
ui/migrations/__init__.py
ui/templates/duavariabel.html
ui/templates/index.html
ui/templates/tigavariabel.html
algebra_collections-1.1.dist-info/License
algebra_collections-1.1.dist-info/METADATA
algebra_collections-1.1.dist-info/WHEEL
algebra_collections-1.1.dist-info/top_level.txt
algebra_collections-1.1.dist-info/RECORD
