Metadata-Version: 2.1
Name: algebra-collections
Version: 1.1
Summary: Simple algebra blueprint and linear equation algorithm
Home-page: https://github.com/Alif4141/Algebra
Author: Kelompok 7 PBPU
Author-email: khaliffmanrahmat@gmail.com
Maintainer: Khaliffman Rahmat Hilal
Maintainer-email: alifkill@student.ub.ac.id
License: MIT
Keywords: django package algebra linear_equations
Platform: UNKNOWN
Classifier: Environment :: Web Environment
Classifier: Framework :: Django
Classifier: Intended Audience :: Developers
Classifier: License :: OSI Approved :: MIT License
Classifier: Operating System :: OS Independent
Classifier: Programming Language :: Python :: 3
Classifier: Programming Language :: Python :: 3 :: Only
Classifier: Programming Language :: Python :: 3.5
Classifier: Programming Language :: Python :: 3.6
Classifier: Programming Language :: Python :: 3.7
Classifier: Programming Language :: Python :: 3.8
Classifier: Programming Language :: Python :: 3.9
Classifier: Topic :: Software Development :: Libraries :: Python Modules
License-File: License
